marvin_python_common/VERSION
marvin_python_common/__init__.py
marvin_python_common/config.py
marvin_python_common/data.py
marvin_python_common/data_source_provider.py
marvin_python_common/exceptions.py
marvin_python_common/http_client.py
marvin_python_common/log.py
marvin_python_common/profiling.py
marvin_python_common/utils.py
marvin_python_common-0.0.0.2.dist-info/DESCRIPTION.rst
marvin_python_common-0.0.0.2.dist-info/METADATA
marvin_python_common-0.0.0.2.dist-info/RECORD
marvin_python_common-0.0.0.2.dist-info/WHEEL
marvin_python_common-0.0.0.2.dist-info/metadata.json
marvin_python_common-0.0.0.2.dist-info/top_level.txt
